{"nodes": [{"id": "c_users_duyma_desktop_arastir_starter_src_lib_pptx_test_ts", "label": "test.ts", "file_type": "code", "source_file": "C:\\Users\\duyma\\Desktop\\arastir-starter\\src\\lib\\pptx\\test.ts", "source_location": "L1"}, {"id": "pptx_test_runtest", "label": "runTest()", "file_type": "code", "source_file": "C:\\Users\\duyma\\Desktop\\arastir-starter\\src\\lib\\pptx\\test.ts", "source_location": "L6"}], "edges": [{"source": "c_users_duyma_desktop_arastir_starter_src_lib_pptx_test_ts", "target": "c_users_duyma_desktop_arastir_starter_src_lib_pptx_generator_ts", "relation": "imports_from", "context": "import", "confidence": "EXTRACTED", "source_file": "C:\\Users\\duyma\\Desktop\\arastir-starter\\src\\lib\\pptx\\test.ts", "source_location": "L1", "weight": 1.0}, {"source": "c_users_duyma_desktop_arastir_starter_src_lib_pptx_test_ts", "target": "pptx_generator_generatepptxreport", "relation": "imports", "context": "import", "confidence": "EXTRACTED", "source_file": "C:\\Users\\duyma\\Desktop\\arastir-starter\\src\\lib\\pptx\\test.ts", "source_location": "L1", "weight": 1.0}, {"source": "c_users_duyma_desktop_arastir_starter_src_lib_pptx_test_ts", "target": "c_users_duyma_desktop_arastir_starter_src_types_research_ts", "relation": "imports_from", "context": "import", "confidence": "EXTRACTED", "source_file": "C:\\Users\\duyma\\Desktop\\arastir-starter\\src\\lib\\pptx\\test.ts", "source_location": "L2", "weight": 1.0}, {"source": "c_users_duyma_desktop_arastir_starter_src_lib_pptx_test_ts", "target": "types_research_reportdata", "relation": "imports", "context": "import", "confidence": "EXTRACTED", "source_file": "C:\\Users\\duyma\\Desktop\\arastir-starter\\src\\lib\\pptx\\test.ts", "source_location": "L2", "weight": 1.0}, {"source": "c_users_duyma_desktop_arastir_starter_src_lib_pptx_test_ts", "target": "fs", "relation": "imports_from", "context": "import", "confidence": "EXTRACTED", "source_file": "C:\\Users\\duyma\\Desktop\\arastir-starter\\src\\lib\\pptx\\test.ts", "source_location": "L3", "weight": 1.0}, {"source": "c_users_duyma_desktop_arastir_starter_src_lib_pptx_test_ts", "target": "path", "relation": "imports_from", "context": "import", "confidence": "EXTRACTED", "source_file": "C:\\Users\\duyma\\Desktop\\arastir-starter\\src\\lib\\pptx\\test.ts", "source_location": "L4", "weight": 1.0}, {"source": "c_users_duyma_desktop_arastir_starter_src_lib_pptx_test_ts", "target": "pptx_test_runtest", "relation": "contains", "confidence": "EXTRACTED", "source_file": "C:\\Users\\duyma\\Desktop\\arastir-starter\\src\\lib\\pptx\\test.ts", "source_location": "L6", "weight": 1.0}], "raw_calls": [{"caller_nid": "pptx_test_runtest", "callee": "log", "is_member_call": true, "source_file": "C:\\Users\\duyma\\Desktop\\arastir-starter\\src\\lib\\pptx\\test.ts", "source_location": "L7"}, {"caller_nid": "pptx_test_runtest", "callee": "join", "is_member_call": true, "source_file": "C:\\Users\\duyma\\Desktop\\arastir-starter\\src\\lib\\pptx\\test.ts", "source_location": "L9"}, {"caller_nid": "pptx_test_runtest", "callee": "log", "is_member_call": true, "source_file": "C:\\Users\\duyma\\Desktop\\arastir-starter\\src\\lib\\pptx\\test.ts", "source_location": "L10"}, {"caller_nid": "pptx_test_runtest", "callee": "readFileSync", "is_member_call": true, "source_file": "C:\\Users\\duyma\\Desktop\\arastir-starter\\src\\lib\\pptx\\test.ts", "source_location": "L11"}, {"caller_nid": "pptx_test_runtest", "callee": "parse", "is_member_call": true, "source_file": "C:\\Users\\duyma\\Desktop\\arastir-starter\\src\\lib\\pptx\\test.ts", "source_location": "L12"}, {"caller_nid": "pptx_test_runtest", "callee": "join", "is_member_call": true, "source_file": "C:\\Users\\duyma\\Desktop\\arastir-starter\\src\\lib\\pptx\\test.ts", "source_location": "L14"}, {"caller_nid": "pptx_test_runtest", "callee": "existsSync", "is_member_call": true, "source_file": "C:\\Users\\duyma\\Desktop\\arastir-starter\\src\\lib\\pptx\\test.ts", "source_location": "L15"}, {"caller_nid": "pptx_test_runtest", "callee": "mkdirSync", "is_member_call": true, "source_file": "C:\\Users\\duyma\\Desktop\\arastir-starter\\src\\lib\\pptx\\test.ts", "source_location": "L16"}, {"caller_nid": "pptx_test_runtest", "callee": "replace", "is_member_call": true, "source_file": "C:\\Users\\duyma\\Desktop\\arastir-starter\\src\\lib\\pptx\\test.ts", "source_location": "L19"}, {"caller_nid": "pptx_test_runtest", "callee": "toISOString", "is_member_call": true, "source_file": "C:\\Users\\duyma\\Desktop\\arastir-starter\\src\\lib\\pptx\\test.ts", "source_location": "L19"}, {"caller_nid": "pptx_test_runtest", "callee": "join", "is_member_call": true, "source_file": "C:\\Users\\duyma\\Desktop\\arastir-starter\\src\\lib\\pptx\\test.ts", "source_location": "L20"}, {"caller_nid": "pptx_test_runtest", "callee": "log", "is_member_call": true, "source_file": "C:\\Users\\duyma\\Desktop\\arastir-starter\\src\\lib\\pptx\\test.ts", "source_location": "L22"}, {"caller_nid": "pptx_test_runtest", "callee": "generatePptxReport", "is_member_call": false, "source_file": "C:\\Users\\duyma\\Desktop\\arastir-starter\\src\\lib\\pptx\\test.ts", "source_location": "L23"}]}